calf_milp/__init__.py
calf_milp/_version.py
calf_milp/calf_milp.py
calf_milp/tests/__init__.py
calf_milp/tests/test_common.py
calf_milp/tests/test_template.py
calf_milp-0.1.8.dist-info/LICENSE
calf_milp-0.1.8.dist-info/METADATA
calf_milp-0.1.8.dist-info/WHEEL
calf_milp-0.1.8.dist-info/top_level.txt
calf_milp-0.1.8.dist-info/RECORD
